etherscanlabel/__init__.py
etherscanlabel/etherscanlabel.py
etherscanlabel/label_category_list.csv
etherscanlabel-0.1.1.dist-info/LICENSE
etherscanlabel-0.1.1.dist-info/METADATA
etherscanlabel-0.1.1.dist-info/WHEEL
etherscanlabel-0.1.1.dist-info/entry_points.txt
etherscanlabel-0.1.1.dist-info/top_level.txt
etherscanlabel-0.1.1.dist-info/RECORD
