Metadata-Version: 2.1
Name: etherscanlabel
Version: 0.1.1
Summary: An out-of-the-box ehterscan label crawler, you can use it to get all the labels info from etherscan.
Home-page: https://github.com/pixelhegel/Etherscan-Label-Crawler
Author: Pixelhegel
Author-email: Pixelhegel@gmail.com
License: MIT License
Keywords: etherscan label crawler
Classifier: License :: OSI Approved :: MIT License
Classifier: Natural Language :: English
Classifier: Programming Language :: Python :: 3
Classifier: Programming Language :: Python :: 3.6
Classifier: Programming Language :: Python :: 3.7
Classifier: Programming Language :: Python :: 3.8
Classifier: Programming Language :: Python :: 3.9
License-File: LICENSE
Requires-Dist: beautifulsoup4
Requires-Dist: docopt
Requires-Dist: notiondict
Requires-Dist: pandas
Requires-Dist: requests
Requires-Dist: setuptools
Requires-Dist: tqdm
